odoo/addons/base_external_dbsource_sqlite/README.rst
odoo/addons/base_external_dbsource_sqlite/__init__.py
odoo/addons/base_external_dbsource_sqlite/__manifest__.py
odoo/addons/base_external_dbsource_sqlite/demo/base_external_dbsource.xml
odoo/addons/base_external_dbsource_sqlite/i18n/base_external_dbsource_sqlite.pot
odoo/addons/base_external_dbsource_sqlite/i18n/de.po
odoo/addons/base_external_dbsource_sqlite/i18n/es.po
odoo/addons/base_external_dbsource_sqlite/i18n/hr.po
odoo/addons/base_external_dbsource_sqlite/i18n/it.po
odoo/addons/base_external_dbsource_sqlite/i18n/nl_NL.po
odoo/addons/base_external_dbsource_sqlite/i18n/pt_BR.po
odoo/addons/base_external_dbsource_sqlite/i18n/sl.po
odoo/addons/base_external_dbsource_sqlite/i18n/tr.po
odoo/addons/base_external_dbsource_sqlite/models/__init__.py
odoo/addons/base_external_dbsource_sqlite/models/base_external_dbsource.py
odoo/addons/base_external_dbsource_sqlite/readme/CONFIGURE.md
odoo/addons/base_external_dbsource_sqlite/readme/CONTRIBUTORS.md
odoo/addons/base_external_dbsource_sqlite/readme/DESCRIPTION.md
odoo/addons/base_external_dbsource_sqlite/readme/INSTALL.md
odoo/addons/base_external_dbsource_sqlite/readme/ROADMAP.md
odoo/addons/base_external_dbsource_sqlite/readme/USAGE.md
odoo/addons/base_external_dbsource_sqlite/static/description/icon.png
odoo/addons/base_external_dbsource_sqlite/static/description/index.html
odoo/addons/base_external_dbsource_sqlite/tests/__init__.py
odoo/addons/base_external_dbsource_sqlite/tests/test_base_external_dbsource.py
odoo_addon_base_external_dbsource_sqlite-17.0.1.0.0.3.dist-info/METADATA
odoo_addon_base_external_dbsource_sqlite-17.0.1.0.0.3.dist-info/WHEEL
odoo_addon_base_external_dbsource_sqlite-17.0.1.0.0.3.dist-info/top_level.txt
odoo_addon_base_external_dbsource_sqlite-17.0.1.0.0.3.dist-info/RECORD
