Metadata-Version: 2.1
Name: odoo-addon-base_external_dbsource_sqlite
Version: 17.0.1.0.0.3
Requires-Python: >=3.10
Requires-Dist: odoo-addon-base_external_dbsource>=17.0dev,<17.1dev
Requires-Dist: odoo>=17.0a,<17.1dev
Requires-Dist: sqlalchemy
Summary: External Database Source - SQLite
Home-page: https://github.com/OCA/server-backend
License: LGPL-3
Author: Daniel Reis, LasLabs, Odoo Community Association (OCA)
Author-email: support@odoo-community.org
Classifier: Programming Language :: Python
Classifier: Framework :: Odoo
Classifier: Framework :: Odoo :: 17.0
Classifier: License :: OSI Approved :: GNU Lesser General Public License v3 (LGPLv3)
